tetra3/__init__.py
tetra3/breadth_first_combinations.py
tetra3/cedar_detect_client.py
tetra3/cedar_detect_pb2.py
tetra3/cedar_detect_pb2.pyi
tetra3/cedar_detect_pb2_grpc.py
tetra3/fov_util.py
tetra3/tetra3.py
tetra3/cli/__init__.py
tetra3/cli/generate_database.py
tetra3/data/default_database.npz
cedar_solve-0.5.1.dist-info/LICENSE.txt
cedar_solve-0.5.1.dist-info/METADATA
cedar_solve-0.5.1.dist-info/WHEEL
cedar_solve-0.5.1.dist-info/entry_points.txt
cedar_solve-0.5.1.dist-info/top_level.txt
cedar_solve-0.5.1.dist-info/RECORD
