Metadata-Version: 2.1
Name: cedar-solve
Version: 0.5.1
Summary: A fast lost-in-space plate solver for star trackers. Forked from esa/tetra3.
Author: Steven Rosenthal
License: Apache License
Project-URL: docs, https://tetra3.readthedocs.io/en/latest/
Project-URL: Source, https://github.com/smroid/cedar-solve
Project-URL: Issues, https://github.com/smroid/cedar-solve/issues
Project-URL: Releases, https://github.com/smroid/cedar-solve/releases
Keywords: astronomy
Classifier: License :: OSI Approved :: Apache Software License
Classifier: Development Status :: 4 - Beta
Classifier: Programming Language :: Python :: 3 :: Only
Classifier: Intended Audience :: Science/Research
Classifier: Intended Audience :: Developers
Classifier: Topic :: Scientific/Engineering :: Astronomy
Requires-Python: >=3.8
License-File: LICENSE.txt
Requires-Dist: numpy <2,>=1.21.1
Requires-Dist: Pillow <9,>=8.3.1
Requires-Dist: scipy <2,>=1.7.1
Provides-Extra: cedar-detect
Requires-Dist: grpcio ; extra == 'cedar-detect'
Requires-Dist: protobuf ; extra == 'cedar-detect'
Provides-Extra: dev
Requires-Dist: pytest ; extra == 'dev'
Requires-Dist: build ; extra == 'dev'
Requires-Dist: grpcio-tools ; extra == 'dev'
Provides-Extra: docs
Requires-Dist: sphinx ; extra == 'docs'
Requires-Dist: sphinx-rtd-theme ; extra == 'docs'
